{
  "$schema": "http://json-schema.org/schema#",
  "type": "object",
  "title": "The Root Schema of event OFF",
  "description": "ITxPT S03P01 TiGR Protocol - Event OFF JSON Schema",
  "required": [
    "EvtOFF",
    "Header"
  ],
  "properties": {
    "EvtOFF": {
      "$id": "#/properties/EvtOFF",
      "type": "object",
      "title": "The Evtoff Schema",
      "required": [
        "ACP",
        "ACS",
        "APU",
        "BRKSTS",
        "CAC",
        "CHS",
        "CMT",
        "CPP",
        "CSE",
        "DCC",
        "EEC",
        "EET",
        "EPC",
        "EVD",
        "EXT",
        "FOD",
        "GEAR",
        "HBT",
        "HEP",
        "ITT",
        "IVT",
        "LBT",
        "LRO",
        "PAC",
        "PBR",
        "PROGON",
        "RPM",
        "RPT",
        "SMX",
        "SOC",
        "SPC",
        "STP",
        "SWA",
        "TBC",
        "TBV",
        "TMX",
        "TRM",
        "TTID",
        "TTSTS",
        "VAC",
        "VB",
        "VHM",
        "VSE"
      ],
      "properties": {
        "ACP": {
          "$id": "#/properties/EvtOFF/properties/ACP",
          "type": "integer",
          "title": "The Acp Schema",          
          "examples": [
            4
          ]
        },
        "ACS": {
          "$id": "#/properties/EvtOFF/properties/ACS",
          "type": "integer",
          "title": "The Acs Schema",          
          "examples": [
            1
          ]
        },
        "APU": {
          "$id": "#/properties/EvtOFF/properties/APU",
          "type": "integer",
          "title": "The Apu Schema",          
          "examples": [
            1
          ]
        },
        "BRKSTS": {
          "$id": "#/properties/EvtOFF/properties/BRKSTS",
          "type": "integer",
          "title": "The Brksts Schema",          
          "examples": [
            0
          ]
        },
        "CAC": {
          "$id": "#/properties/EvtOFF/properties/CAC",
          "type": "integer",
          "title": "The Cac Schema",          
          "examples": [
            2
          ]
        },
        "CHS": {
          "$id": "#/properties/EvtOFF/properties/CHS",
          "type": "integer",
          "title": "The Chs Schema",          
          "examples": [
            4
          ]
        },
        "CMT": {
          "$id": "#/properties/EvtOFF/properties/CMT",
          "type": "integer",
          "title": "The Cmt Schema",          
          "examples": [
            90
          ]
        },
        "CPP": {
          "$id": "#/properties/EvtOFF/properties/CPP",
          "type": "integer",
          "title": "The Cpp Schema",          
          "examples": [
            11
          ]
        },
        "CSE": {
          "$id": "#/properties/EvtOFF/properties/CSE",
          "type": "integer",
          "title": "The Cse Schema",          
          "examples": [
            3
          ]
        },
        "DCC": {
          "$id": "#/properties/EvtOFF/properties/DCC",
          "type": "integer",
          "title": "The Dcc Schema",
          
          "examples": [
            3
          ]
        },
        "EEC": {
          "$id": "#/properties/EvtOFF/properties/EEC",
          "type": "integer",
          "title": "The Eec Schema",          
          "examples": [
            15
          ]
        },
        "EET": {
          "$id": "#/properties/EvtOFF/properties/EET",
          "type": "integer",
          "title": "The Eet Schema",          
          "examples": [
            1100
          ]
        },
        "EPC": {
          "$id": "#/properties/EvtOFF/properties/EPC",
          "type": "integer",
          "title": "The Epc Schema",          
          "examples": [
            50
          ]
        },
        "EVD": {
          "$id": "#/properties/EvtOFF/properties/EVD",
          "type": "integer",
          "title": "The Evd Schema",          
          "examples": [
            253
          ]
        },
        "EXT": {
          "$id": "#/properties/EvtOFF/properties/EXT",
          "type": "integer",
          "title": "The Ext Schema",          
          "examples": [
            25
          ]
        },
        "FOD": {
          "$id": "#/properties/EvtOFF/properties/FOD",
          "type": "integer",
          "title": "The Fod Schema",          
          "examples": [
            3260
          ]
        },
        "GEAR": {
          "$id": "#/properties/EvtOFF/properties/GEAR",
          "type": "integer",
          "title": "The Gear Schema",          
          "examples": [
            1
          ]
        },
        "HBT": {
          "$id": "#/properties/EvtOFF/properties/HBT",
          "type": "integer",
          "title": "The Hbt Schema",          
          "examples": [
            35
          ]
        },
        "HEP": {
          "$id": "#/properties/EvtOFF/properties/HEP",
          "type": "integer",
          "title": "The Hep Schema",          
          "examples": [
            0
          ]
        },
        "ITT": {
          "$id": "#/properties/EvtOFF/properties/ITT",
          "type": "integer",
          "title": "The Itt Schema",          
          "examples": [
            28
          ]
        },
        "IVT": {
          "$id": "#/properties/EvtOFF/properties/IVT",
          "type": "integer",
          "title": "The Ivt Schema",          
          "examples": [
            27
          ]
        },
        "LBT": {
          "$id": "#/properties/EvtOFF/properties/LBT",
          "type": "integer",
          "title": "The Lbt Schema",          
          "examples": [
            30
          ]
        },
        "LRO": {
          "$id": "#/properties/EvtOFF/properties/LRO",
          "type": "integer",
          "title": "The Lro Schema",          
          "examples": [
            2147483647
          ]
        },
        "PAC": {
          "$id": "#/properties/EvtOFF/properties/PAC",
          "type": "integer",
          "title": "The Pac Schema",          
          "examples": [
            26
          ]
        },
        "PBR": {
          "$id": "#/properties/EvtOFF/properties/PBR",
          "type": "integer",
          "title": "The Pbr Schema",          
          "examples": [
            0
          ]
        },
        "PROGON": {
          "$id": "#/properties/EvtOFF/properties/PROGON",
          "type": "integer",
          "title": "The Progon Schema",          
          "examples": [
            1289
          ]
        },
        "RPM": {
          "$id": "#/properties/EvtOFF/properties/RPM",
          "type": "integer",
          "title": "The Rpm Schema",          
          "examples": [
            742
          ]
        },
        "RPT": {
          "$id": "#/properties/EvtOFF/properties/RPT",
          "type": "integer",
          "title": "The Rpt Schema",          
          "examples": [
            0
          ]
        },
        "SMX": {
          "$id": "#/properties/EvtOFF/properties/SMX",
          "type": "integer",
          "title": "The Smx Schema",          
          "examples": [
            34
          ]
        },
        "SOC": {
          "$id": "#/properties/EvtOFF/properties/SOC",
          "type": "integer",
          "title": "The Soc Schema",          
          "examples": [
            47
          ]
        },
        "SPC": {
          "$id": "#/properties/EvtOFF/properties/SPC",
          "type": "integer",
          "title": "The Spc Schema",          
          "examples": [
            2
          ]
        },
        "STP": {
          "$id": "#/properties/EvtOFF/properties/STP",
          "type": "integer",
          "title": "The Stp Schema",          
          "examples": [
            0
          ]
        },
        "SWA": {
          "$id": "#/properties/EvtOFF/properties/SWA",
          "type": "integer",
          "title": "The Swa Schema",          
          "examples": [
            53
          ]
        },
        "TBC": {
          "$id": "#/properties/EvtOFF/properties/TBC",
          "type": "integer",
          "title": "The Tbc Schema",          
          "examples": [
            16
          ]
        },
        "TBV": {
          "$id": "#/properties/EvtOFF/properties/TBV",
          "type": "integer",
          "title": "The Tbv Schema",          
          "examples": [
            741
          ]
        },
        "TMX": {
          "$id": "#/properties/EvtOFF/properties/TMX",
          "type": "integer",
          "title": "The Tmx Schema",          
          "examples": [
            54
          ]
        },
        "TRM": {
          "$id": "#/properties/EvtOFF/properties/TRM",
          "type": "integer",
          "title": "The Trm Schema",          
          "examples": [
            41
          ]
        },
        "TTID": {
          "$id": "#/properties/EvtOFF/properties/TTID",
          "type": "integer",
          "title": "The Ttid Schema",          
          "examples": [
            2147483647
          ]
        },
        "TTSTS": {
          "$id": "#/properties/EvtOFF/properties/TTSTS",
          "type": "integer",
          "title": "The Ttsts Schema",          
          "examples": [
            2147483647
          ]
        },
        "VAC": {
          "$id": "#/properties/EvtOFF/properties/VAC",
          "type": "integer",
          "title": "The Vac Schema",          
          "examples": [
            24
          ]
        },
        "VB": {
          "$id": "#/properties/EvtOFF/properties/VB",
          "type": "integer",
          "title": "The Vb Schema",          
          "examples": [
            264
          ]
        },
        "VHM": {
          "$id": "#/properties/EvtOFF/properties/VHM",
          "type": "integer",
          "title": "The Vhm Schema",          
          "examples": [
            2
          ]
        },
        "VSE": {
          "$id": "#/properties/EvtOFF/properties/VSE",
          "type": "integer",
          "title": "The Vse Schema",          
          "examples": [
            41
          ]
        }
      }
    },
    "Header": {
      "$id": "#/properties/Header",
      "type": "object",
      "title": "The Header Schema",
      "required": [
        "CODE",
        "DST",
        "EVTDATE",
        "GPSInfo",
        "ID",
        "PROG",
        "SENDDATE",
        "SERVERNAME",
        "SRVDATE",
        "TX",
        "TYPE",
        "VIN"
      ],
      "properties": {
        "CODE": {
          "$id": "#/properties/Header/properties/CODE",
          "type": "string",
          "title": "The Code Schema",          
          "examples": [
            "EC10"
          ],
          "pattern": "^(.*)$"
        },
        "DST": {
          "$id": "#/properties/Header/properties/DST",
          "type": "integer",
          "title": "The Dst Schema",
          "examples": [
            240636
          ]
        },
        "EVTDATE": {
          "$id": "#/properties/Header/properties/EVTDATE",
          "type": "integer",
          "title": "The Evtdate Schema",
          "examples": [
            1492714346
          ]
        },
        "GPSInfo": {
          "$id": "#/properties/Header/properties/GPSInfo",
          "type": "object",
          "title": "The Gpsinfo Schema",
          "required": [
            "ALT",
            "DOP",            
            "LAT",
            "LON"  
          ],
          "properties": {
            "ALT": {
              "$id": "#/properties/Header/properties/GPSInfo/properties/ALT",
              "type": "integer",
              "title": "The Alt Schema",
              "examples": [
                260
              ]
            },
            "DOP": {
              "$id": "#/properties/Header/properties/GPSInfo/properties/DOP",
              "type": "integer",
              "title": "The Dop Schema",
              "examples": [
                25
              ]
            },
            "GNSSType": {
              "$id": "#/properties/Header/properties/GPSInfo/properties/GNSSType",
              "type": "string",
              "title": "The Gnsstype Schema",
              "enum": ["GPS", "GLONASS", "GALILEO", "BEIDOU", "IRNSS", "Other"],
              "examples": [
                "GLONASS"
              ],
              "pattern": "^(.*)$"
            },
            "HEAD": {
              "$id": "#/properties/Header/properties/GPSInfo/properties/HEAD",
              "type": "integer",
              "title": "The Head Schema",
              "examples": [
                0
              ]
            },
            "LAT": {
              "$id": "#/properties/Header/properties/GPSInfo/properties/LAT",
              "type": "integer",
              "title": "The Lat Schema",
              "examples": [
                2932530
              ]
            },
            "LON": {
              "$id": "#/properties/Header/properties/GPSInfo/properties/LON",
              "type": "integer",
              "title": "The Lon Schema",
              "examples": [
                155604
              ]
            },
            "NUMSAT": {
              "$id": "#/properties/Header/properties/GPSInfo/properties/NUMSAT",
              "type": "integer",
              "title": "The Numsat Schema",
              "examples": [
                7
              ]
            }
          }
        },
        "ID": {
          "$id": "#/properties/Header/properties/ID",
          "type": "integer",
          "title": "The Id Schema",
          "examples": [
            4
          ]
        },
        "PROG": {
          "$id": "#/properties/Header/properties/PROG",
          "type": "integer",
          "title": "The Prog Schema",
          "examples": [
            1345
          ]
        },
        "SENDDATE": {
          "$id": "#/properties/Header/properties/SENDDATE",
          "type": "integer",
          "title": "The Senddate Schema",
          "examples": [
            1492714386
          ]
        },
        "SERVERNAME": {
          "$id": "#/properties/Header/properties/SERVERNAME",
          "type": "string",
          "title": "The Servername Schema",
          "examples": [
            "ABC"
          ],
          "pattern": "^(.*)$"
        },
        "SRVDATE": {
          "$id": "#/properties/Header/properties/SRVDATE",
          "type": "integer",
          "title": "The Srvdate Schema",
          "examples": [
            1492714366
          ]
        },
         "TIMEZONE": {
          "$id": "#/properties/Header/properties/TIMEZONE",
          "type": "string",
          "title": "The Timezone Schema",
          "examples": [
            "UTC+01:00"
          ],
          "pattern": "^(.*)$"
        },
        "TX": {
          "$id": "#/properties/Header/properties/TX",
          "type": "integer",
          "title": "The Tx Schema",
          "enum": [0, 1, 3],
          "examples": [
            3
          ]
        },
        "TYPE": {
          "$id": "#/properties/Header/properties/TYPE",
          "type": "string",
          "title": "The Type Schema",
          "examples": [
            "HEADER_ONLY"
          ],
          "pattern": "^(.*)$"
        },
        "VIN": {
          "$id": "#/properties/Header/properties/VIN",
          "type": "string",
          "title": "The Vin Schema",
          "examples": [
            "VIN00000000000001"
          ],
          "pattern": "^(.*)$"
        }
      }
    }
  }
}
